{
    "key": "group_cb_text_quote",
    "title": "CB Text Quote",
    "fields": [
        {
            "key": "field_cb_text_quote_title",
            "label": "CB Text Quote",
            "name": "",
            "aria-label": "",
            "type": "message",
            "instructions": "",
            "required": 0,
            "conditional_logic": false,
            "wrapper": {
                "width": "",
                "class": "",
                "id": ""
            },
            "message": "",
            "esc_html": 0,
            "new_lines": "wpautop"
        },
        {
            "key": "field_67c72909248e1",
            "label": "Text",
            "name": "",
            "aria-label": "",
            "type": "tab",
            "instructions": "",
            "required": 0,
            "conditional_logic": 0,
            "wrapper": {
                "width": "",
                "class": "",
                "id": ""
            },
            "placement": "top",
            "endpoint": 0,
            "selected": 0
        },
        {
            "key": "field_67c728e3248dc",
            "label": "Title",
            "name": "title",
            "aria-label": "",
            "type": "text",
            "instructions": "",
            "required": 0,
            "conditional_logic": 0,
            "wrapper": {
                "width": "",
                "class": "",
                "id": ""
            },
            "default_value": "",
            "maxlength": "",
            "allow_in_bindings": 0,
            "placeholder": "",
            "prepend": "",
            "append": ""
        },
        {
            "key": "field_67c728ea248dd",
            "label": "Content",
            "name": "content",
            "aria-label": "",
            "type": "textarea",
            "instructions": "",
            "required": 0,
            "conditional_logic": 0,
            "wrapper": {
                "width": "",
                "class": "",
                "id": ""
            },
            "default_value": "",
            "maxlength": "",
            "allow_in_bindings": 0,
            "rows": "",
            "placeholder": "",
            "new_lines": "br"
        },
        {
            "key": "field_67c728f2248de",
            "label": "CTA",
            "name": "cta",
            "aria-label": "",
            "type": "link",
            "instructions": "",
            "required": 0,
            "conditional_logic": 0,
            "wrapper": {
                "width": "",
                "class": "",
                "id": ""
            },
            "return_format": "array",
            "allow_in_bindings": 0
        },
        {
            "key": "field_67c72915248e2",
            "label": "Quote",
            "name": "",
            "aria-label": "",
            "type": "tab",
            "instructions": "",
            "required": 0,
            "conditional_logic": 0,
            "wrapper": {
                "width": "",
                "class": "",
                "id": ""
            },
            "placement": "top",
            "endpoint": 0,
            "selected": 0
        },
        {
            "key": "field_67c728fb248df",
            "label": "Quote",
            "name": "quote",
            "aria-label": "",
            "type": "text",
            "instructions": "",
            "required": 0,
            "conditional_logic": 0,
            "wrapper": {
                "width": "",
                "class": "",
                "id": ""
            },
            "default_value": "",
            "maxlength": "",
            "allow_in_bindings": 1,
            "placeholder": "",
            "prepend": "",
            "append": ""
        },
        {
            "key": "field_67c72903248e0",
            "label": "Attribution",
            "name": "attribution",
            "aria-label": "",
            "type": "text",
            "instructions": "",
            "required": 0,
            "conditional_logic": 0,
            "wrapper": {
                "width": "",
                "class": "",
                "id": ""
            },
            "default_value": "",
            "maxlength": "",
            "allow_in_bindings": 0,
            "placeholder": "",
            "prepend": "",
            "append": ""
        }
    ],
    "location": [
        [
            {
                "param": "block",
                "operator": "==",
                "value": "acf\/cb-text-quote"
            }
        ]
    ],
    "menu_order": 0,
    "position": "normal",
    "style": "default",
    "label_placement": "top",
    "instruction_placement": "label",
    "hide_on_screen": "",
    "active": true,
    "description": "",
    "show_in_rest": 0,
    "modified": 1741175649
}
